git_add_co_author/__init__.py
git_add_co_author/__main__.py
git_add_co_author-0.4.2.dist-info/WHEEL
git_add_co_author-0.4.2.dist-info/METADATA
git_add_co_author-0.4.2.dist-info/RECORD
