Metadata-Version: 2.1
Name: git-add-co-author
Version: 0.4.2
Summary: Git Add Co-Author is a simple cli tool that allows you to easily add co-authors to your Git commits.
Author: Sanskar Jethi
Author-email: sansyrox@gmail.com
Requires-Python: >=3.8,<4.0
Classifier: Programming Language :: Python :: 3
Classifier: Programming Language :: Python :: 3.8
Classifier: Programming Language :: Python :: 3.9
Classifier: Programming Language :: Python :: 3.10
Classifier: Programming Language :: Python :: 3.11
Requires-Dist: click (>=8.1.3,<9.0.0)
Requires-Dist: requests (>=2.29.0,<3.0.0)
